{"commitInfo":{"timestamp":1776448141742,"operation":"WRITE","operationParameters":{"mode":"Append","partitionBy":"[]"},"readVersion":4,"isolationLevel":"Serializable","isBlindAppend":true,"operationMetrics":{"numFiles":"14","numOutputRows":"100000","numOutputBytes":"5040245"},"engineInfo":"Apache-Spark/4.1.1 Delta-Lake/4.1.0","txnId":"93a2b6a8-d6b7-46e2-9771-785d8af76eac"}}
{"add":{"path":"part-00000-0e60cbc0-70a4-4cb5-b621-bc2624fb8316-c000.snappy.parquet","partitionValues":{},"size":361544,"modificationTime":1776448141692,"dataChange":true,"stats":"{\"numRecords\":7168,\"minValues\":{\"reading_id\":\"001104d6-2314-82fe-9cef-4511c345\",\"sensor_id\":\"2c386245-7993-6340-58de-21d43312\",\"timestamp_ms\":1735567200000,\"location\":{\"latitude\":-45.4148,\"longitude\":-159.3711,\"altitude_meters\":-86.0,\"place_name\":\"Bergen, Vestland, Norway\"},\"precipitation_mm\":0.01,\"rain_intensity\":\"RAIN_INTENSITY_HEAVY\",\"temperature_celsius\":-14.8,\"humidity_percent\":3.0,\"pressure_hpa\":759.0,\"wind_speed_kmh\":1.0,\"wind_direction_degrees\":0.1,\"battery_level_percent\":5,\"signal_strength_dbm\":-95},\"maxValues\":{\"reading_id\":\"ffff7a22-8520-0c77-9d47-cf824bf2\",\"sensor_id\":\"ffb43aae-7b42-f1f1-03b6-3d56a2a7\",\"timestamp_ms\":1736018280000,\"location\":{\"latitude\":64.1466,\"longitude\":167.7181,\"altitude_meters\":2400.0,\"place_name\":\"Tokyo, Kantō, Japan\"},\"precipitation_mm\":13.79,\"rain_intensity\":\"RAIN_INTENSITY_NONE\",\"temperature_celsius\":52.0,\"humidity_percent\":100.0,\"pressure_hpa\":1027.0,\"wind_speed_kmh\":65.6,\"wind_direction_degrees\":359.9,\"battery_level_percent\":5,\"signal_strength_dbm\":-20},\"nullCount\":{\"reading_id\":0,\"sensor_id\":0,\"timestamp_ms\":0,\"location\":{\"latitude\":0,\"longitude\":0,\"altitude_meters\":358,\"place_name\":0},\"precipitation_mm\":3907,\"rain_intensity\":0,\"is_raining\":3907,\"temperature_celsius\":4,\"humidity_percent\":0,\"pressure_hpa\":0,\"wind_speed_kmh\":0,\"wind_direction_degrees\":0,\"battery_level_percent\":0,\"signal_strength_dbm\":0}}"}}
{"add":{"path":"part-00001-678f8a0e-8f6c-4d7c-8642-b0ce371705e8-c000.snappy.parquet","partitionValues":{},"size":361076,"modificationTime":1776448141704,"dataChange":true,"stats":"{\"numRecords\":7168,\"minValues\":{\"reading_id\":\"0004aac7-34c9-f3ec-3502-27d75ebf\",\"sensor_id\":\"2c386245-7993-6340-58de-21d43312\",\"timestamp_ms\":1736018280000,\"location\":{\"latitude\":-45.4148,\"longitude\":-159.3711,\"altitude_meters\":-86.0,\"place_name\":\"Bergen, Vestland, Norway\"},\"precipitation_mm\":0.01,\"rain_intensity\":\"RAIN_INTENSITY_HEAVY\",\"temperature_celsius\":-14.7,\"humidity_percent\":3.1,\"pressure_hpa\":759.0,\"wind_speed_kmh\":1.0,\"wind_direction_degrees\":0.1,\"battery_level_percent\":5,\"signal_strength_dbm\":-95},\"maxValues\":{\"reading_id\":\"fffd7377-4e39-660d-1b2a-0fcee8af\",\"sensor_id\":\"ffb43aae-7b42-f1f1-03b6-3d56a2a7\",\"timestamp_ms\":1736469360000,\"location\":{\"latitude\":64.1466,\"longitude\":167.7181,\"altitude_meters\":2400.0,\"place_name\":\"Tokyo, Kantō, Japan\"},\"precipitation_mm\":12.73,\"rain_intensity\":\"RAIN_INTENSITY_NONE\",\"temperature_celsius\":51.7,\"humidity_percent\":100.0,\"pressure_hpa\":1027.0,\"wind_speed_kmh\":64.9,\"wind_direction_degrees\":359.9,\"battery_level_percent\":5,\"signal_strength_dbm\":-20},\"nullCount\":{\"reading_id\":0,\"sensor_id\":0,\"timestamp_ms\":0,\"location\":{\"latitude\":0,\"longitude\":0,\"altitude_meters\":359,\"place_name\":0},\"precipitation_mm\":3887,\"rain_intensity\":0,\"is_raining\":3887,\"temperature_celsius\":2,\"humidity_percent\":0,\"pressure_hpa\":0,\"wind_speed_kmh\":0,\"wind_direction_degrees\":2,\"battery_level_percent\":0,\"signal_strength_dbm\":0}}"}}
{"add":{"path":"part-00002-69973df8-a78f-4efb-9113-f6a48a42524e-c000.snappy.parquet","partitionValues":{},"size":360896,"modificationTime":1776448141688,"dataChange":true,"stats":"{\"numRecords\":7168,\"minValues\":{\"reading_id\":\"000ec7d2-afe9-ef3a-f996-98de2d1b\",\"sensor_id\":\"2c386245-7993-6340-58de-21d43312\",\"timestamp_ms\":1736469360000,\"location\":{\"latitude\":-45.4148,\"longitude\":-159.3711,\"altitude_meters\":-86.0,\"place_name\":\"Bergen, Vestland, Norway\"},\"precipitation_mm\":0.01,\"rain_intensity\":\"RAIN_INTENSITY_HEAVY\",\"temperature_celsius\":-14.4,\"humidity_percent\":3.0,\"pressure_hpa\":756.7,\"wind_speed_kmh\":1.0,\"wind_direction_degrees\":0.1,\"battery_level_percent\":5,\"signal_strength_dbm\":-95},\"maxValues\":{\"reading_id\":\"fff9a87d-9734-8594-daa8-a21ab4a0\",\"sensor_id\":\"ffb43aae-7b42-f1f1-03b6-3d56a2a7\",\"timestamp_ms\":1736921700000,\"location\":{\"latitude\":64.1466,\"longitude\":167.7181,\"altitude_meters\":2400.0,\"place_name\":\"Tokyo, Kantō, Japan\"},\"precipitation_mm\":13.12,\"rain_intensity\":\"RAIN_INTENSITY_NONE\",\"temperature_celsius\":52.0,\"humidity_percent\":100.0,\"pressure_hpa\":1027.0,\"wind_speed_kmh\":65.4,\"wind_direction_degrees\":359.9,\"battery_level_percent\":5,\"signal_strength_dbm\":-20},\"nullCount\":{\"reading_id\":0,\"sensor_id\":0,\"timestamp_ms\":0,\"location\":{\"latitude\":0,\"longitude\":0,\"altitude_meters\":358,\"place_name\":0},\"precipitation_mm\":3869,\"rain_intensity\":0,\"is_raining\":3869,\"temperature_celsius\":4,\"humidity_percent\":0,\"pressure_hpa\":0,\"wind_speed_kmh\":0,\"wind_direction_degrees\":0,\"battery_level_percent\":0,\"signal_strength_dbm\":0}}"}}
{"add":{"path":"part-00003-964d1e2f-921c-426b-9232-23d90897c6ac-c000.snappy.parquet","partitionValues":{},"size":361048,"modificationTime":1776448141717,"dataChange":true,"stats":"{\"numRecords\":7168,\"minValues\":{\"reading_id\":\"0005f038-eebd-c334-130f-fdfc7e5e\",\"sensor_id\":\"2c386245-7993-6340-58de-21d43312\",\"timestamp_ms\":1736921700000,\"location\":{\"latitude\":-45.4148,\"longitude\":-159.3711,\"altitude_meters\":-86.0,\"place_name\":\"Bergen, Vestland, Norway\"},\"precipitation_mm\":0.01,\"rain_intensity\":\"RAIN_INTENSITY_HEAVY\",\"temperature_celsius\":-14.9,\"humidity_percent\":3.0,\"pressure_hpa\":756.4,\"wind_speed_kmh\":1.1,\"wind_direction_degrees\":0.1,\"battery_level_percent\":5,\"signal_strength_dbm\":-95},\"maxValues\":{\"reading_id\":\"fff0c849-548f-b355-66e3-6d360055\",\"sensor_id\":\"ffb43aae-7b42-f1f1-03b6-3d56a2a7\",\"timestamp_ms\":1737372780000,\"location\":{\"latitude\":64.1466,\"longitude\":167.7181,\"altitude_meters\":2400.0,\"place_name\":\"Tokyo, Kantō, Japan\"},\"precipitation_mm\":13.72,\"rain_intensity\":\"RAIN_INTENSITY_NONE\",\"temperature_celsius\":51.8,\"humidity_percent\":100.0,\"pressure_hpa\":1027.0,\"wind_speed_kmh\":75.7,\"wind_direction_degrees\":359.9,\"battery_level_percent\":5,\"signal_strength_dbm\":-20},\"nullCount\":{\"reading_id\":0,\"sensor_id\":0,\"timestamp_ms\":0,\"location\":{\"latitude\":0,\"longitude\":0,\"altitude_meters\":359,\"place_name\":0},\"precipitation_mm\":3866,\"rain_intensity\":0,\"is_raining\":3866,\"temperature_celsius\":5,\"humidity_percent\":0,\"pressure_hpa\":0,\"wind_speed_kmh\":0,\"wind_direction_degrees\":1,\"battery_level_percent\":0,\"signal_strength_dbm\":0}}"}}
{"add":{"path":"part-00004-d2298037-ddcc-45cc-b585-7103862cff17-c000.snappy.parquet","partitionValues":{},"size":361276,"modificationTime":1776448141723,"dataChange":true,"stats":"{\"numRecords\":7168,\"minValues\":{\"reading_id\":\"000a3889-d59c-2ae2-ddae-a9a3c5fe\",\"sensor_id\":\"2c386245-7993-6340-58de-21d43312\",\"timestamp_ms\":1737372780000,\"location\":{\"latitude\":-45.4148,\"longitude\":-159.3711,\"altitude_meters\":-86.0,\"place_name\":\"Bergen, Vestland, Norway\"},\"precipitation_mm\":0.01,\"rain_intensity\":\"RAIN_INTENSITY_HEAVY\",\"temperature_celsius\":-14.9,\"humidity_percent\":3.0,\"pressure_hpa\":756.3,\"wind_speed_kmh\":1.0,\"wind_direction_degrees\":0.1,\"battery_level_percent\":5,\"signal_strength_dbm\":-95},\"maxValues\":{\"reading_id\":\"fffe1c61-f1bd-8d40-dffb-023d05b4\",\"sensor_id\":\"ffb43aae-7b42-f1f1-03b6-3d56a2a7\",\"timestamp_ms\":1737823860000,\"location\":{\"latitude\":64.1466,\"longitude\":167.7181,\"altitude_meters\":2400.0,\"place_name\":\"Tokyo, Kantō, Japan\"},\"precipitation_mm\":13.27,\"rain_intensity\":\"RAIN_INTENSITY_NONE\",\"temperature_celsius\":51.9,\"humidity_percent\":100.0,\"pressure_hpa\":1027.0,\"wind_speed_kmh\":71.4,\"wind_direction_degrees\":359.9,\"battery_level_percent\":5,\"signal_strength_dbm\":-20},\"nullCount\":{\"reading_id\":0,\"sensor_id\":0,\"timestamp_ms\":0,\"location\":{\"latitude\":0,\"longitude\":0,\"altitude_meters\":358,\"place_name\":0},\"precipitation_mm\":3960,\"rain_intensity\":0,\"is_raining\":3960,\"temperature_celsius\":5,\"humidity_percent\":0,\"pressure_hpa\":0,\"wind_speed_kmh\":0,\"wind_direction_degrees\":3,\"battery_level_percent\":0,\"signal_strength_dbm\":0}}"}}
{"add":{"path":"part-00005-7f87d218-afbf-40a0-ae2e-7a8ffeadc477-c000.snappy.parquet","partitionValues":{},"size":361155,"modificationTime":1776448141694,"dataChange":true,"stats":"{\"numRecords\":7168,\"minValues\":{\"reading_id\":\"0000ea69-1dd1-2027-49eb-3205a3cd\",\"sensor_id\":\"2c386245-7993-6340-58de-21d43312\",\"timestamp_ms\":1737825120000,\"location\":{\"latitude\":-45.4148,\"longitude\":-159.3711,\"altitude_meters\":-86.0,\"place_name\":\"Bergen, Vestland, Norway\"},\"precipitation_mm\":0.03,\"rain_intensity\":\"RAIN_INTENSITY_HEAVY\",\"temperature_celsius\":-14.7,\"humidity_percent\":3.1,\"pressure_hpa\":756.3,\"wind_speed_kmh\":1.0,\"wind_direction_degrees\":0.1,\"battery_level_percent\":5,\"signal_strength_dbm\":-95},\"maxValues\":{\"reading_id\":\"fff9c063-ddc9-755a-d7b0-e8c03bc0\",\"sensor_id\":\"ffb43aae-7b42-f1f1-03b6-3d56a2a7\",\"timestamp_ms\":1738276200000,\"location\":{\"latitude\":64.1466,\"longitude\":167.7181,\"altitude_meters\":2400.0,\"place_name\":\"Tokyo, Kantō, Japan\"},\"precipitation_mm\":12.78,\"rain_intensity\":\"RAIN_INTENSITY_NONE\",\"temperature_celsius\":52.0,\"humidity_percent\":100.0,\"pressure_hpa\":1027.0,\"wind_speed_kmh\":77.0,\"wind_direction_degrees\":359.9,\"battery_level_percent\":5,\"signal_strength_dbm\":-20},\"nullCount\":{\"reading_id\":0,\"sensor_id\":0,\"timestamp_ms\":0,\"location\":{\"latitude\":0,\"longitude\":0,\"altitude_meters\":358,\"place_name\":0},\"precipitation_mm\":3847,\"rain_intensity\":0,\"is_raining\":3847,\"temperature_celsius\":3,\"humidity_percent\":0,\"pressure_hpa\":0,\"wind_speed_kmh\":0,\"wind_direction_degrees\":1,\"battery_level_percent\":0,\"signal_strength_dbm\":0}}"}}
{"add":{"path":"part-00006-63fb44d0-3933-4663-aa78-ae0c1689bccc-c000.snappy.parquet","partitionValues":{},"size":361552,"modificationTime":1776448141715,"dataChange":true,"stats":"{\"numRecords\":7168,\"minValues\":{\"reading_id\":\"0004087a-c5d8-8197-4206-ed448cf4\",\"sensor_id\":\"2c386245-7993-6340-58de-21d43312\",\"timestamp_ms\":1738276200000,\"location\":{\"latitude\":-45.4148,\"longitude\":-159.3711,\"altitude_meters\":-86.0,\"place_name\":\"Bergen, Vestland, Norway\"},\"precipitation_mm\":0.02,\"rain_intensity\":\"RAIN_INTENSITY_HEAVY\",\"temperature_celsius\":-15.0,\"humidity_percent\":3.0,\"pressure_hpa\":756.5,\"wind_speed_kmh\":1.0,\"wind_direction_degrees\":0.1,\"battery_level_percent\":5,\"signal_strength_dbm\":-95},\"maxValues\":{\"reading_id\":\"ffe9af30-bfb2-c55e-7cc4-cf2cf52b\",\"sensor_id\":\"ffb43aae-7b42-f1f1-03b6-3d56a2a7\",\"timestamp_ms\":1738727280000,\"location\":{\"latitude\":64.1466,\"longitude\":167.7181,\"altitude_meters\":2400.0,\"place_name\":\"Tokyo, Kantō, Japan\"},\"precipitation_mm\":12.52,\"rain_intensity\":\"RAIN_INTENSITY_NONE\",\"temperature_celsius\":51.9,\"humidity_percent\":100.0,\"pressure_hpa\":1027.0,\"wind_speed_kmh\":66.5,\"wind_direction_degrees\":359.9,\"battery_level_percent\":5,\"signal_strength_dbm\":-20},\"nullCount\":{\"reading_id\":0,\"sensor_id\":0,\"timestamp_ms\":0,\"location\":{\"latitude\":0,\"longitude\":0,\"altitude_meters\":359,\"place_name\":0},\"precipitation_mm\":3863,\"rain_intensity\":0,\"is_raining\":3863,\"temperature_celsius\":5,\"humidity_percent\":0,\"pressure_hpa\":0,\"wind_speed_kmh\":0,\"wind_direction_degrees\":0,\"battery_level_percent\":0,\"signal_strength_dbm\":0}}"}}
{"add":{"path":"part-00007-10d5baaf-f306-4ba2-b444-7016a9c305ab-c000.snappy.parquet","partitionValues":{},"size":360947,"modificationTime":1776448141728,"dataChange":true,"stats":"{\"numRecords\":7168,\"minValues\":{\"reading_id\":\"00022a8c-c06c-0cf0-425e-c11bb5cc\",\"sensor_id\":\"2c386245-7993-6340-58de-21d43312\",\"timestamp_ms\":1738727280000,\"location\":{\"latitude\":-45.4148,\"longitude\":-159.3711,\"altitude_meters\":-86.0,\"place_name\":\"Bergen, Vestland, Norway\"},\"precipitation_mm\":0.01,\"rain_intensity\":\"RAIN_INTENSITY_HEAVY\",\"temperature_celsius\":-14.7,\"humidity_percent\":3.0,\"pressure_hpa\":756.2,\"wind_speed_kmh\":1.0,\"wind_direction_degrees\":0.1,\"battery_level_percent\":5,\"signal_strength_dbm\":-95},\"maxValues\":{\"reading_id\":\"fffefa57-5644-55a6-13c0-4d5d666f\",\"sensor_id\":\"ffb43aae-7b42-f1f1-03b6-3d56a2a7\",\"timestamp_ms\":1739179620000,\"location\":{\"latitude\":64.1466,\"longitude\":167.7181,\"altitude_meters\":2400.0,\"place_name\":\"Tokyo, Kantō, Japan\"},\"precipitation_mm\":12.97,\"rain_intensity\":\"RAIN_INTENSITY_NONE\",\"temperature_celsius\":51.8,\"humidity_percent\":100.0,\"pressure_hpa\":1027.0,\"wind_speed_kmh\":78.7,\"wind_direction_degrees\":359.8,\"battery_level_percent\":5,\"signal_strength_dbm\":-20},\"nullCount\":{\"reading_id\":0,\"sensor_id\":0,\"timestamp_ms\":0,\"location\":{\"latitude\":0,\"longitude\":0,\"altitude_meters\":358,\"place_name\":0},\"precipitation_mm\":3882,\"rain_intensity\":0,\"is_raining\":3882,\"temperature_celsius\":3,\"humidity_percent\":0,\"pressure_hpa\":0,\"wind_speed_kmh\":0,\"wind_direction_degrees\":3,\"battery_level_percent\":0,\"signal_strength_dbm\":0}}"}}
{"add":{"path":"part-00008-4ae8126c-c1d7-4cac-a91d-fd3b3f0883dc-c000.snappy.parquet","partitionValues":{},"size":360857,"modificationTime":1776448141717,"dataChange":true,"stats":"{\"numRecords\":7168,\"minValues\":{\"reading_id\":\"001dce3b-5f14-6ad5-77ad-ba4baf34\",\"sensor_id\":\"2c386245-7993-6340-58de-21d43312\",\"timestamp_ms\":1739179620000,\"location\":{\"latitude\":-45.4148,\"longitude\":-159.3711,\"altitude_meters\":-86.0,\"place_name\":\"Bergen, Vestland, Norway\"},\"precipitation_mm\":0.02,\"rain_intensity\":\"RAIN_INTENSITY_HEAVY\",\"temperature_celsius\":-15.0,\"humidity_percent\":3.0,\"pressure_hpa\":756.2,\"wind_speed_kmh\":1.1,\"wind_direction_degrees\":0.2,\"battery_level_percent\":5,\"signal_strength_dbm\":-95},\"maxValues\":{\"reading_id\":\"fffe5946-250b-27dc-aa6f-8c92a6b5\",\"sensor_id\":\"ffb43aae-7b42-f1f1-03b6-3d56a2a7\",\"timestamp_ms\":1739630700000,\"location\":{\"latitude\":64.1466,\"longitude\":167.7181,\"altitude_meters\":2400.0,\"place_name\":\"Tokyo, Kantō, Japan\"},\"precipitation_mm\":12.73,\"rain_intensity\":\"RAIN_INTENSITY_NONE\",\"temperature_celsius\":52.0,\"humidity_percent\":100.0,\"pressure_hpa\":1027.0,\"wind_speed_kmh\":65.0,\"wind_direction_degrees\":359.9,\"battery_level_percent\":5,\"signal_strength_dbm\":-20},\"nullCount\":{\"reading_id\":0,\"sensor_id\":0,\"timestamp_ms\":0,\"location\":{\"latitude\":0,\"longitude\":0,\"altitude_meters\":359,\"place_name\":0},\"precipitation_mm\":3843,\"rain_intensity\":0,\"is_raining\":3843,\"temperature_celsius\":7,\"humidity_percent\":0,\"pressure_hpa\":0,\"wind_speed_kmh\":0,\"wind_direction_degrees\":1,\"battery_level_percent\":0,\"signal_strength_dbm\":0}}"}}
{"add":{"path":"part-00009-d0423497-8872-4f06-9345-c6bea82b539d-c000.snappy.parquet","partitionValues":{},"size":361113,"modificationTime":1776448141721,"dataChange":true,"stats":"{\"numRecords\":7168,\"minValues\":{\"reading_id\":\"00030caf-2cf7-32c1-bfae-eb5a2aa5\",\"sensor_id\":\"2c386245-7993-6340-58de-21d43312\",\"timestamp_ms\":1739630700000,\"location\":{\"latitude\":-45.4148,\"longitude\":-159.3711,\"altitude_meters\":-86.0,\"place_name\":\"Bergen, Vestland, Norway\"},\"precipitation_mm\":0.01,\"rain_intensity\":\"RAIN_INTENSITY_HEAVY\",\"temperature_celsius\":-14.9,\"humidity_percent\":3.0,\"pressure_hpa\":757.8,\"wind_speed_kmh\":1.0,\"wind_direction_degrees\":0.3,\"battery_level_percent\":5,\"signal_strength_dbm\":-95},\"maxValues\":{\"reading_id\":\"fff63043-7724-3df7-460b-a978f035\",\"sensor_id\":\"ffb43aae-7b42-f1f1-03b6-3d56a2a7\",\"timestamp_ms\":1740081780000,\"location\":{\"latitude\":64.1466,\"longitude\":167.7181,\"altitude_meters\":2400.0,\"place_name\":\"Tokyo, Kantō, Japan\"},\"precipitation_mm\":12.76,\"rain_intensity\":\"RAIN_INTENSITY_NONE\",\"temperature_celsius\":51.9,\"humidity_percent\":100.0,\"pressure_hpa\":1027.0,\"wind_speed_kmh\":73.7,\"wind_direction_degrees\":359.9,\"battery_level_percent\":5,\"signal_strength_dbm\":-20},\"nullCount\":{\"reading_id\":0,\"sensor_id\":0,\"timestamp_ms\":0,\"location\":{\"latitude\":0,\"longitude\":0,\"altitude_meters\":358,\"place_name\":0},\"precipitation_mm\":3862,\"rain_intensity\":0,\"is_raining\":3862,\"temperature_celsius\":4,\"humidity_percent\":0,\"pressure_hpa\":0,\"wind_speed_kmh\":0,\"wind_direction_degrees\":2,\"battery_level_percent\":0,\"signal_strength_dbm\":0}}"}}
{"add":{"path":"part-00010-339e717b-9769-4c30-b434-d1ee9c5a5de7-c000.snappy.parquet","partitionValues":{},"size":361318,"modificationTime":1776448141718,"dataChange":true,"stats":"{\"numRecords\":7168,\"minValues\":{\"reading_id\":\"00193c02-e901-0159-4e57-9ac6b792\",\"sensor_id\":\"2c386245-7993-6340-58de-21d43312\",\"timestamp_ms\":1740083040000,\"location\":{\"latitude\":-45.4148,\"longitude\":-159.3711,\"altitude_meters\":-86.0,\"place_name\":\"Bergen, Vestland, Norway\"},\"precipitation_mm\":0.03,\"rain_intensity\":\"RAIN_INTENSITY_HEAVY\",\"temperature_celsius\":-14.9,\"humidity_percent\":3.1,\"pressure_hpa\":756.4,\"wind_speed_kmh\":1.1,\"wind_direction_degrees\":0.1,\"battery_level_percent\":5,\"signal_strength_dbm\":-95},\"maxValues\":{\"reading_id\":\"fffe2a2d-f265-ed0f-4524-05883cde\",\"sensor_id\":\"ffb43aae-7b42-f1f1-03b6-3d56a2a7\",\"timestamp_ms\":1740534120000,\"location\":{\"latitude\":64.1466,\"longitude\":167.7181,\"altitude_meters\":2400.0,\"place_name\":\"Tokyo, Kantō, Japan\"},\"precipitation_mm\":14.17,\"rain_intensity\":\"RAIN_INTENSITY_NONE\",\"temperature_celsius\":51.6,\"humidity_percent\":100.0,\"pressure_hpa\":1027.0,\"wind_speed_kmh\":73.2,\"wind_direction_degrees\":359.9,\"battery_level_percent\":5,\"signal_strength_dbm\":-20},\"nullCount\":{\"reading_id\":0,\"sensor_id\":0,\"timestamp_ms\":0,\"location\":{\"latitude\":0,\"longitude\":0,\"altitude_meters\":358,\"place_name\":0},\"precipitation_mm\":3864,\"rain_intensity\":0,\"is_raining\":3864,\"temperature_celsius\":3,\"humidity_percent\":0,\"pressure_hpa\":0,\"wind_speed_kmh\":0,\"wind_direction_degrees\":1,\"battery_level_percent\":0,\"signal_strength_dbm\":0}}"}}
{"add":{"path":"part-00011-45a87e0d-b974-4f59-bc34-fd12eaa5e922-c000.snappy.parquet","partitionValues":{},"size":361119,"modificationTime":1776448141739,"dataChange":true,"stats":"{\"numRecords\":7168,\"minValues\":{\"reading_id\":\"0008c99a-f649-bd9a-9f39-f7c97aaf\",\"sensor_id\":\"2c386245-7993-6340-58de-21d43312\",\"timestamp_ms\":1740534120000,\"location\":{\"latitude\":-45.4148,\"longitude\":-159.3711,\"altitude_meters\":-86.0,\"place_name\":\"Bergen, Vestland, Norway\"},\"precipitation_mm\":0.01,\"rain_intensity\":\"RAIN_INTENSITY_HEAVY\",\"temperature_celsius\":-14.9,\"humidity_percent\":3.1,\"pressure_hpa\":757.6,\"wind_speed_kmh\":1.0,\"wind_direction_degrees\":0.1,\"battery_level_percent\":5,\"signal_strength_dbm\":-95},\"maxValues\":{\"reading_id\":\"fffdbe36-da07-8f4a-4439-d81a300a\",\"sensor_id\":\"ffb43aae-7b42-f1f1-03b6-3d56a2a7\",\"timestamp_ms\":1740985200000,\"location\":{\"latitude\":64.1466,\"longitude\":167.7181,\"altitude_meters\":2400.0,\"place_name\":\"Tokyo, Kantō, Japan\"},\"precipitation_mm\":12.73,\"rain_intensity\":\"RAIN_INTENSITY_NONE\",\"temperature_celsius\":51.5,\"humidity_percent\":100.0,\"pressure_hpa\":1027.0,\"wind_speed_kmh\":69.0,\"wind_direction_degrees\":359.9,\"battery_level_percent\":5,\"signal_strength_dbm\":-20},\"nullCount\":{\"reading_id\":0,\"sensor_id\":0,\"timestamp_ms\":0,\"location\":{\"latitude\":0,\"longitude\":0,\"altitude_meters\":359,\"place_name\":0},\"precipitation_mm\":3832,\"rain_intensity\":0,\"is_raining\":3832,\"temperature_celsius\":4,\"humidity_percent\":0,\"pressure_hpa\":0,\"wind_speed_kmh\":0,\"wind_direction_degrees\":1,\"battery_level_percent\":0,\"signal_strength_dbm\":0}}"}}
{"add":{"path":"part-00012-cf5ac914-b704-4b86-b86b-7011ba801ea4-c000.snappy.parquet","partitionValues":{},"size":361344,"modificationTime":1776448141679,"dataChange":true,"stats":"{\"numRecords\":7168,\"minValues\":{\"reading_id\":\"001f48ab-126b-ec1f-2227-5af67f1b\",\"sensor_id\":\"2c386245-7993-6340-58de-21d43312\",\"timestamp_ms\":1740985200000,\"location\":{\"latitude\":-45.4148,\"longitude\":-159.3711,\"altitude_meters\":-86.0,\"place_name\":\"Bergen, Vestland, Norway\"},\"precipitation_mm\":0.02,\"rain_intensity\":\"RAIN_INTENSITY_HEAVY\",\"temperature_celsius\":-14.8,\"humidity_percent\":3.0,\"pressure_hpa\":756.1,\"wind_speed_kmh\":1.0,\"wind_direction_degrees\":0.1,\"battery_level_percent\":5,\"signal_strength_dbm\":-95},\"maxValues\":{\"reading_id\":\"fff7bb2e-42a4-db15-02e1-924404ed\",\"sensor_id\":\"ffb43aae-7b42-f1f1-03b6-3d56a2a7\",\"timestamp_ms\":1741437540000,\"location\":{\"latitude\":64.1466,\"longitude\":167.7181,\"altitude_meters\":2400.0,\"place_name\":\"Tokyo, Kantō, Japan\"},\"precipitation_mm\":12.59,\"rain_intensity\":\"RAIN_INTENSITY_NONE\",\"temperature_celsius\":51.8,\"humidity_percent\":100.0,\"pressure_hpa\":1027.0,\"wind_speed_kmh\":64.2,\"wind_direction_degrees\":359.9,\"battery_level_percent\":5,\"signal_strength_dbm\":-20},\"nullCount\":{\"reading_id\":0,\"sensor_id\":0,\"timestamp_ms\":0,\"location\":{\"latitude\":0,\"longitude\":0,\"altitude_meters\":358,\"place_name\":0},\"precipitation_mm\":3916,\"rain_intensity\":0,\"is_raining\":3916,\"temperature_celsius\":8,\"humidity_percent\":0,\"pressure_hpa\":0,\"wind_speed_kmh\":0,\"wind_direction_degrees\":1,\"battery_level_percent\":0,\"signal_strength_dbm\":0}}"}}
{"add":{"path":"part-00013-5cf0bf53-fe6e-4fb9-ad98-5ced71cf2b7f-c000.snappy.parquet","partitionValues":{},"size":345000,"modificationTime":1776448141720,"dataChange":true,"stats":"{\"numRecords\":6816,\"minValues\":{\"reading_id\":\"000454fa-7489-2fa7-b956-adbe4439\",\"sensor_id\":\"2c386245-7993-6340-58de-21d43312\",\"timestamp_ms\":1741437540000,\"location\":{\"latitude\":-45.4148,\"longitude\":-159.3711,\"altitude_meters\":-86.0,\"place_name\":\"Bergen, Vestland, Norway\"},\"precipitation_mm\":0.01,\"rain_intensity\":\"RAIN_INTENSITY_HEAVY\",\"temperature_celsius\":-15.0,\"humidity_percent\":3.0,\"pressure_hpa\":756.4,\"wind_speed_kmh\":1.0,\"wind_direction_degrees\":0.1,\"battery_level_percent\":5,\"signal_strength_dbm\":-95},\"maxValues\":{\"reading_id\":\"ffd8fe05-f1d8-1ee6-4348-f6616b22\",\"sensor_id\":\"ffb43aae-7b42-f1f1-03b6-3d56a2a7\",\"timestamp_ms\":1741865940000,\"location\":{\"latitude\":64.1466,\"longitude\":167.7181,\"altitude_meters\":2400.0,\"place_name\":\"Tokyo, Kantō, Japan\"},\"precipitation_mm\":13.81,\"rain_intensity\":\"RAIN_INTENSITY_NONE\",\"temperature_celsius\":52.0,\"humidity_percent\":100.0,\"pressure_hpa\":1027.0,\"wind_speed_kmh\":76.6,\"wind_direction_degrees\":359.9,\"battery_level_percent\":5,\"signal_strength_dbm\":-20},\"nullCount\":{\"reading_id\":0,\"sensor_id\":0,\"timestamp_ms\":0,\"location\":{\"latitude\":0,\"longitude\":0,\"altitude_meters\":341,\"place_name\":0},\"precipitation_mm\":3706,\"rain_intensity\":0,\"is_raining\":3706,\"temperature_celsius\":6,\"humidity_percent\":0,\"pressure_hpa\":0,\"wind_speed_kmh\":0,\"wind_direction_degrees\":0,\"battery_level_percent\":0,\"signal_strength_dbm\":0}}"}}
