{"commitInfo":{"timestamp":1776448146685,"operation":"WRITE","operationParameters":{"mode":"Append","partitionBy":"[]"},"readVersion":7,"isolationLevel":"Serializable","isBlindAppend":true,"operationMetrics":{"numFiles":"14","numOutputRows":"100000","numOutputBytes":"5039602"},"engineInfo":"Apache-Spark/4.1.1 Delta-Lake/4.1.0","txnId":"b4674a2e-dc1a-483a-a354-38dca691c3b1"}}
{"add":{"path":"part-00000-9957df8f-7930-406e-979e-60c36a274fc9-c000.snappy.parquet","partitionValues":{},"size":361004,"modificationTime":1776448146678,"dataChange":true,"stats":"{\"numRecords\":7168,\"minValues\":{\"reading_id\":\"001025aa-0265-b6b3-a4f3-30fe726b\",\"sensor_id\":\"2c386245-7993-6340-58de-21d43312\",\"timestamp_ms\":1754467200000,\"location\":{\"latitude\":-45.4148,\"longitude\":-159.3711,\"altitude_meters\":-86.0,\"place_name\":\"Bergen, Vestland, Norway\"},\"precipitation_mm\":0.02,\"rain_intensity\":\"RAIN_INTENSITY_HEAVY\",\"temperature_celsius\":-15.0,\"humidity_percent\":3.1,\"pressure_hpa\":756.2,\"wind_speed_kmh\":1.0,\"wind_direction_degrees\":0.1,\"battery_level_percent\":5,\"signal_strength_dbm\":-95},\"maxValues\":{\"reading_id\":\"fffec5c4-f390-932e-ac85-f3902f5b\",\"sensor_id\":\"ffb43aae-7b42-f1f1-03b6-3d56a2a7\",\"timestamp_ms\":1754918280000,\"location\":{\"latitude\":64.1466,\"longitude\":167.7181,\"altitude_meters\":2400.0,\"place_name\":\"Tokyo, Kantō, Japan\"},\"precipitation_mm\":13.61,\"rain_intensity\":\"RAIN_INTENSITY_NONE\",\"temperature_celsius\":51.8,\"humidity_percent\":100.0,\"pressure_hpa\":1027.0,\"wind_speed_kmh\":73.0,\"wind_direction_degrees\":359.8,\"battery_level_percent\":5,\"signal_strength_dbm\":-20},\"nullCount\":{\"reading_id\":0,\"sensor_id\":0,\"timestamp_ms\":0,\"location\":{\"latitude\":0,\"longitude\":0,\"altitude_meters\":358,\"place_name\":0},\"precipitation_mm\":3833,\"rain_intensity\":0,\"is_raining\":3833,\"temperature_celsius\":6,\"humidity_percent\":0,\"pressure_hpa\":0,\"wind_speed_kmh\":0,\"wind_direction_degrees\":0,\"battery_level_percent\":0,\"signal_strength_dbm\":0}}"}}
{"add":{"path":"part-00001-826c0503-df32-40a1-a5bc-84fea458f7dc-c000.snappy.parquet","partitionValues":{},"size":361194,"modificationTime":1776448146664,"dataChange":true,"stats":"{\"numRecords\":7168,\"minValues\":{\"reading_id\":\"000170f1-4fe8-6d3f-929e-7d6e18a4\",\"sensor_id\":\"2c386245-7993-6340-58de-21d43312\",\"timestamp_ms\":1754918280000,\"location\":{\"latitude\":-45.4148,\"longitude\":-159.3711,\"altitude_meters\":-86.0,\"place_name\":\"Bergen, Vestland, Norway\"},\"precipitation_mm\":0.01,\"rain_intensity\":\"RAIN_INTENSITY_HEAVY\",\"temperature_celsius\":-14.9,\"humidity_percent\":3.0,\"pressure_hpa\":756.1,\"wind_speed_kmh\":1.0,\"wind_direction_degrees\":0.1,\"battery_level_percent\":5,\"signal_strength_dbm\":-95},\"maxValues\":{\"reading_id\":\"fffebf9e-cde5-93e1-7bd7-87280514\",\"sensor_id\":\"ffb43aae-7b42-f1f1-03b6-3d56a2a7\",\"timestamp_ms\":1755369360000,\"location\":{\"latitude\":64.1466,\"longitude\":167.7181,\"altitude_meters\":2400.0,\"place_name\":\"Tokyo, Kantō, Japan\"},\"precipitation_mm\":12.4,\"rain_intensity\":\"RAIN_INTENSITY_NONE\",\"temperature_celsius\":51.6,\"humidity_percent\":100.0,\"pressure_hpa\":1027.0,\"wind_speed_kmh\":71.3,\"wind_direction_degrees\":359.8,\"battery_level_percent\":5,\"signal_strength_dbm\":-20},\"nullCount\":{\"reading_id\":0,\"sensor_id\":0,\"timestamp_ms\":0,\"location\":{\"latitude\":0,\"longitude\":0,\"altitude_meters\":359,\"place_name\":0},\"precipitation_mm\":3798,\"rain_intensity\":0,\"is_raining\":3798,\"temperature_celsius\":3,\"humidity_percent\":0,\"pressure_hpa\":0,\"wind_speed_kmh\":0,\"wind_direction_degrees\":2,\"battery_level_percent\":0,\"signal_strength_dbm\":0}}"}}
{"add":{"path":"part-00002-0c61be31-876b-4f95-855a-fe7ad47115c1-c000.snappy.parquet","partitionValues":{},"size":360998,"modificationTime":1776448146678,"dataChange":true,"stats":"{\"numRecords\":7168,\"minValues\":{\"reading_id\":\"000e279e-b28f-c154-6b08-a738c56a\",\"sensor_id\":\"2c386245-7993-6340-58de-21d43312\",\"timestamp_ms\":1755369360000,\"location\":{\"latitude\":-45.4148,\"longitude\":-159.3711,\"altitude_meters\":-86.0,\"place_name\":\"Bergen, Vestland, Norway\"},\"precipitation_mm\":0.02,\"rain_intensity\":\"RAIN_INTENSITY_HEAVY\",\"temperature_celsius\":-14.9,\"humidity_percent\":3.3,\"pressure_hpa\":756.6,\"wind_speed_kmh\":1.0,\"wind_direction_degrees\":0.1,\"battery_level_percent\":5,\"signal_strength_dbm\":-95},\"maxValues\":{\"reading_id\":\"fff70d57-055a-04b4-2c7b-e91e12f1\",\"sensor_id\":\"ffb43aae-7b42-f1f1-03b6-3d56a2a7\",\"timestamp_ms\":1755821700000,\"location\":{\"latitude\":64.1466,\"longitude\":167.7181,\"altitude_meters\":2400.0,\"place_name\":\"Tokyo, Kantō, Japan\"},\"precipitation_mm\":12.68,\"rain_intensity\":\"RAIN_INTENSITY_NONE\",\"temperature_celsius\":52.0,\"humidity_percent\":100.0,\"pressure_hpa\":1027.0,\"wind_speed_kmh\":64.7,\"wind_direction_degrees\":359.9,\"battery_level_percent\":5,\"signal_strength_dbm\":-20},\"nullCount\":{\"reading_id\":0,\"sensor_id\":0,\"timestamp_ms\":0,\"location\":{\"latitude\":0,\"longitude\":0,\"altitude_meters\":358,\"place_name\":0},\"precipitation_mm\":3902,\"rain_intensity\":0,\"is_raining\":3902,\"temperature_celsius\":4,\"humidity_percent\":0,\"pressure_hpa\":0,\"wind_speed_kmh\":0,\"wind_direction_degrees\":2,\"battery_level_percent\":0,\"signal_strength_dbm\":0}}"}}
{"add":{"path":"part-00003-067ed718-0056-4b2f-a969-9d25fbcb10d8-c000.snappy.parquet","partitionValues":{},"size":361308,"modificationTime":1776448146670,"dataChange":true,"stats":"{\"numRecords\":7168,\"minValues\":{\"reading_id\":\"0000a3c4-c502-eadc-a3c6-a4bac2ce\",\"sensor_id\":\"2c386245-7993-6340-58de-21d43312\",\"timestamp_ms\":1755821700000,\"location\":{\"latitude\":-45.4148,\"longitude\":-159.3711,\"altitude_meters\":-86.0,\"place_name\":\"Bergen, Vestland, Norway\"},\"precipitation_mm\":0.01,\"rain_intensity\":\"RAIN_INTENSITY_HEAVY\",\"temperature_celsius\":-14.8,\"humidity_percent\":3.1,\"pressure_hpa\":756.8,\"wind_speed_kmh\":1.0,\"wind_direction_degrees\":0.1,\"battery_level_percent\":5,\"signal_strength_dbm\":-95},\"maxValues\":{\"reading_id\":\"ffce6e65-5282-02fb-5c03-b1c47b6e\",\"sensor_id\":\"ffb43aae-7b42-f1f1-03b6-3d56a2a7\",\"timestamp_ms\":1756272780000,\"location\":{\"latitude\":64.1466,\"longitude\":167.7181,\"altitude_meters\":2400.0,\"place_name\":\"Tokyo, Kantō, Japan\"},\"precipitation_mm\":13.13,\"rain_intensity\":\"RAIN_INTENSITY_NONE\",\"temperature_celsius\":52.0,\"humidity_percent\":100.0,\"pressure_hpa\":1027.0,\"wind_speed_kmh\":68.6,\"wind_direction_degrees\":359.8,\"battery_level_percent\":5,\"signal_strength_dbm\":-20},\"nullCount\":{\"reading_id\":0,\"sensor_id\":0,\"timestamp_ms\":0,\"location\":{\"latitude\":0,\"longitude\":0,\"altitude_meters\":359,\"place_name\":0},\"precipitation_mm\":3816,\"rain_intensity\":0,\"is_raining\":3816,\"temperature_celsius\":7,\"humidity_percent\":0,\"pressure_hpa\":0,\"wind_speed_kmh\":0,\"wind_direction_degrees\":0,\"battery_level_percent\":0,\"signal_strength_dbm\":0}}"}}
{"add":{"path":"part-00004-776182c2-abc3-4aec-acbe-0a86aa18bdb4-c000.snappy.parquet","partitionValues":{},"size":361596,"modificationTime":1776448146681,"dataChange":true,"stats":"{\"numRecords\":7168,\"minValues\":{\"reading_id\":\"00014ea8-340b-67b5-c4f2-d6f2ed26\",\"sensor_id\":\"2c386245-7993-6340-58de-21d43312\",\"timestamp_ms\":1756272780000,\"location\":{\"latitude\":-45.4148,\"longitude\":-159.3711,\"altitude_meters\":-86.0,\"place_name\":\"Bergen, Vestland, Norway\"},\"precipitation_mm\":0.02,\"rain_intensity\":\"RAIN_INTENSITY_HEAVY\",\"temperature_celsius\":-14.9,\"humidity_percent\":3.0,\"pressure_hpa\":756.1,\"wind_speed_kmh\":1.0,\"wind_direction_degrees\":0.1,\"battery_level_percent\":5,\"signal_strength_dbm\":-95},\"maxValues\":{\"reading_id\":\"fffde3bc-342b-8e7b-b573-a188fbe2\",\"sensor_id\":\"ffb43aae-7b42-f1f1-03b6-3d56a2a7\",\"timestamp_ms\":1756723860000,\"location\":{\"latitude\":64.1466,\"longitude\":167.7181,\"altitude_meters\":2400.0,\"place_name\":\"Tokyo, Kantō, Japan\"},\"precipitation_mm\":13.63,\"rain_intensity\":\"RAIN_INTENSITY_NONE\",\"temperature_celsius\":51.6,\"humidity_percent\":100.0,\"pressure_hpa\":1027.0,\"wind_speed_kmh\":77.6,\"wind_direction_degrees\":359.9,\"battery_level_percent\":5,\"signal_strength_dbm\":-20},\"nullCount\":{\"reading_id\":0,\"sensor_id\":0,\"timestamp_ms\":0,\"location\":{\"latitude\":0,\"longitude\":0,\"altitude_meters\":358,\"place_name\":0},\"precipitation_mm\":3853,\"rain_intensity\":0,\"is_raining\":3853,\"temperature_celsius\":5,\"humidity_percent\":0,\"pressure_hpa\":0,\"wind_speed_kmh\":0,\"wind_direction_degrees\":1,\"battery_level_percent\":0,\"signal_strength_dbm\":0}}"}}
{"add":{"path":"part-00005-fa51ef18-dceb-4119-989b-e5d82d8848d0-c000.snappy.parquet","partitionValues":{},"size":361238,"modificationTime":1776448146651,"dataChange":true,"stats":"{\"numRecords\":7168,\"minValues\":{\"reading_id\":\"0010ee84-f6cb-b19e-d9d5-6545c2ce\",\"sensor_id\":\"2c386245-7993-6340-58de-21d43312\",\"timestamp_ms\":1756725120000,\"location\":{\"latitude\":-45.4148,\"longitude\":-159.3711,\"altitude_meters\":-86.0,\"place_name\":\"Bergen, Vestland, Norway\"},\"precipitation_mm\":0.01,\"rain_intensity\":\"RAIN_INTENSITY_HEAVY\",\"temperature_celsius\":-15.0,\"humidity_percent\":3.0,\"pressure_hpa\":756.4,\"wind_speed_kmh\":1.0,\"wind_direction_degrees\":0.1,\"battery_level_percent\":5,\"signal_strength_dbm\":-95},\"maxValues\":{\"reading_id\":\"fffeabe6-9ae3-a925-0929-e9667455\",\"sensor_id\":\"ffb43aae-7b42-f1f1-03b6-3d56a2a7\",\"timestamp_ms\":1757176200000,\"location\":{\"latitude\":64.1466,\"longitude\":167.7181,\"altitude_meters\":2400.0,\"place_name\":\"Tokyo, Kantō, Japan\"},\"precipitation_mm\":13.06,\"rain_intensity\":\"RAIN_INTENSITY_NONE\",\"temperature_celsius\":51.8,\"humidity_percent\":100.0,\"pressure_hpa\":1027.0,\"wind_speed_kmh\":67.3,\"wind_direction_degrees\":359.9,\"battery_level_percent\":5,\"signal_strength_dbm\":-20},\"nullCount\":{\"reading_id\":0,\"sensor_id\":0,\"timestamp_ms\":0,\"location\":{\"latitude\":0,\"longitude\":0,\"altitude_meters\":358,\"place_name\":0},\"precipitation_mm\":3828,\"rain_intensity\":0,\"is_raining\":3828,\"temperature_celsius\":5,\"humidity_percent\":0,\"pressure_hpa\":0,\"wind_speed_kmh\":0,\"wind_direction_degrees\":0,\"battery_level_percent\":0,\"signal_strength_dbm\":0}}"}}
{"add":{"path":"part-00006-53c29f55-9c0a-4191-b285-8bce8a745c7d-c000.snappy.parquet","partitionValues":{},"size":361043,"modificationTime":1776448146679,"dataChange":true,"stats":"{\"numRecords\":7168,\"minValues\":{\"reading_id\":\"0003474f-971c-086e-69bc-8d767859\",\"sensor_id\":\"2c386245-7993-6340-58de-21d43312\",\"timestamp_ms\":1757176200000,\"location\":{\"latitude\":-45.4148,\"longitude\":-159.3711,\"altitude_meters\":-86.0,\"place_name\":\"Bergen, Vestland, Norway\"},\"precipitation_mm\":0.01,\"rain_intensity\":\"RAIN_INTENSITY_HEAVY\",\"temperature_celsius\":-14.8,\"humidity_percent\":3.0,\"pressure_hpa\":756.6,\"wind_speed_kmh\":1.0,\"wind_direction_degrees\":0.1,\"battery_level_percent\":5,\"signal_strength_dbm\":-95},\"maxValues\":{\"reading_id\":\"ffff95b2-07d7-f69e-75e9-361ec00f\",\"sensor_id\":\"ffb43aae-7b42-f1f1-03b6-3d56a2a7\",\"timestamp_ms\":1757627280000,\"location\":{\"latitude\":64.1466,\"longitude\":167.7181,\"altitude_meters\":2400.0,\"place_name\":\"Tokyo, Kantō, Japan\"},\"precipitation_mm\":12.51,\"rain_intensity\":\"RAIN_INTENSITY_NONE\",\"temperature_celsius\":52.0,\"humidity_percent\":100.0,\"pressure_hpa\":1027.0,\"wind_speed_kmh\":70.4,\"wind_direction_degrees\":359.9,\"battery_level_percent\":5,\"signal_strength_dbm\":-20},\"nullCount\":{\"reading_id\":0,\"sensor_id\":0,\"timestamp_ms\":0,\"location\":{\"latitude\":0,\"longitude\":0,\"altitude_meters\":359,\"place_name\":0},\"precipitation_mm\":3817,\"rain_intensity\":0,\"is_raining\":3817,\"temperature_celsius\":6,\"humidity_percent\":0,\"pressure_hpa\":0,\"wind_speed_kmh\":0,\"wind_direction_degrees\":1,\"battery_level_percent\":0,\"signal_strength_dbm\":0}}"}}
{"add":{"path":"part-00007-3799f584-4156-4acd-b1c6-d76243302574-c000.snappy.parquet","partitionValues":{},"size":360893,"modificationTime":1776448146672,"dataChange":true,"stats":"{\"numRecords\":7168,\"minValues\":{\"reading_id\":\"0001d127-0fe2-1aba-1236-f47d6fcb\",\"sensor_id\":\"2c386245-7993-6340-58de-21d43312\",\"timestamp_ms\":1757627280000,\"location\":{\"latitude\":-45.4148,\"longitude\":-159.3711,\"altitude_meters\":-86.0,\"place_name\":\"Bergen, Vestland, Norway\"},\"precipitation_mm\":0.01,\"rain_intensity\":\"RAIN_INTENSITY_HEAVY\",\"temperature_celsius\":-14.7,\"humidity_percent\":3.1,\"pressure_hpa\":756.7,\"wind_speed_kmh\":1.0,\"wind_direction_degrees\":0.1,\"battery_level_percent\":5,\"signal_strength_dbm\":-95},\"maxValues\":{\"reading_id\":\"fff3f140-1971-28e5-303b-6db7df36\",\"sensor_id\":\"ffb43aae-7b42-f1f1-03b6-3d56a2a7\",\"timestamp_ms\":1758079620000,\"location\":{\"latitude\":64.1466,\"longitude\":167.7181,\"altitude_meters\":2400.0,\"place_name\":\"Tokyo, Kantō, Japan\"},\"precipitation_mm\":12.58,\"rain_intensity\":\"RAIN_INTENSITY_NONE\",\"temperature_celsius\":52.0,\"humidity_percent\":100.0,\"pressure_hpa\":1027.0,\"wind_speed_kmh\":64.9,\"wind_direction_degrees\":359.9,\"battery_level_percent\":5,\"signal_strength_dbm\":-20},\"nullCount\":{\"reading_id\":0,\"sensor_id\":0,\"timestamp_ms\":0,\"location\":{\"latitude\":0,\"longitude\":0,\"altitude_meters\":358,\"place_name\":0},\"precipitation_mm\":3884,\"rain_intensity\":0,\"is_raining\":3884,\"temperature_celsius\":7,\"humidity_percent\":0,\"pressure_hpa\":0,\"wind_speed_kmh\":0,\"wind_direction_degrees\":0,\"battery_level_percent\":0,\"signal_strength_dbm\":0}}"}}
{"add":{"path":"part-00008-4d3753b7-41ff-4014-91d0-db43238bb4b5-c000.snappy.parquet","partitionValues":{},"size":360789,"modificationTime":1776448146667,"dataChange":true,"stats":"{\"numRecords\":7168,\"minValues\":{\"reading_id\":\"0005333e-df0e-5d3b-7d9f-97abeb29\",\"sensor_id\":\"2c386245-7993-6340-58de-21d43312\",\"timestamp_ms\":1758079620000,\"location\":{\"latitude\":-45.4148,\"longitude\":-159.3711,\"altitude_meters\":-86.0,\"place_name\":\"Bergen, Vestland, Norway\"},\"precipitation_mm\":0.01,\"rain_intensity\":\"RAIN_INTENSITY_HEAVY\",\"temperature_celsius\":-15.0,\"humidity_percent\":3.0,\"pressure_hpa\":757.9,\"wind_speed_kmh\":1.0,\"wind_direction_degrees\":0.1,\"battery_level_percent\":5,\"signal_strength_dbm\":-95},\"maxValues\":{\"reading_id\":\"fffd0977-3910-d5b6-c3aa-ea4af244\",\"sensor_id\":\"ffb43aae-7b42-f1f1-03b6-3d56a2a7\",\"timestamp_ms\":1758530700000,\"location\":{\"latitude\":64.1466,\"longitude\":167.7181,\"altitude_meters\":2400.0,\"place_name\":\"Tokyo, Kantō, Japan\"},\"precipitation_mm\":12.72,\"rain_intensity\":\"RAIN_INTENSITY_NONE\",\"temperature_celsius\":52.0,\"humidity_percent\":100.0,\"pressure_hpa\":1027.0,\"wind_speed_kmh\":68.9,\"wind_direction_degrees\":359.8,\"battery_level_percent\":5,\"signal_strength_dbm\":-20},\"nullCount\":{\"reading_id\":0,\"sensor_id\":0,\"timestamp_ms\":0,\"location\":{\"latitude\":0,\"longitude\":0,\"altitude_meters\":359,\"place_name\":0},\"precipitation_mm\":3837,\"rain_intensity\":0,\"is_raining\":3837,\"temperature_celsius\":4,\"humidity_percent\":0,\"pressure_hpa\":0,\"wind_speed_kmh\":0,\"wind_direction_degrees\":2,\"battery_level_percent\":0,\"signal_strength_dbm\":0}}"}}
{"add":{"path":"part-00009-bf79a6f2-5987-4343-8eaf-582bd9ff8c09-c000.snappy.parquet","partitionValues":{},"size":361238,"modificationTime":1776448146650,"dataChange":true,"stats":"{\"numRecords\":7168,\"minValues\":{\"reading_id\":\"000b96ee-af52-0ae6-3fc8-10c8a4ae\",\"sensor_id\":\"2c386245-7993-6340-58de-21d43312\",\"timestamp_ms\":1758530700000,\"location\":{\"latitude\":-45.4148,\"longitude\":-159.3711,\"altitude_meters\":-86.0,\"place_name\":\"Bergen, Vestland, Norway\"},\"precipitation_mm\":0.02,\"rain_intensity\":\"RAIN_INTENSITY_HEAVY\",\"temperature_celsius\":-14.8,\"humidity_percent\":3.1,\"pressure_hpa\":758.9,\"wind_speed_kmh\":1.0,\"wind_direction_degrees\":0.2,\"battery_level_percent\":5,\"signal_strength_dbm\":-95},\"maxValues\":{\"reading_id\":\"fff8157c-66b6-2032-fa48-b01651e2\",\"sensor_id\":\"ffb43aae-7b42-f1f1-03b6-3d56a2a7\",\"timestamp_ms\":1758981780000,\"location\":{\"latitude\":64.1466,\"longitude\":167.7181,\"altitude_meters\":2400.0,\"place_name\":\"Tokyo, Kantō, Japan\"},\"precipitation_mm\":13.78,\"rain_intensity\":\"RAIN_INTENSITY_NONE\",\"temperature_celsius\":52.0,\"humidity_percent\":100.0,\"pressure_hpa\":1027.0,\"wind_speed_kmh\":77.3,\"wind_direction_degrees\":359.8,\"battery_level_percent\":5,\"signal_strength_dbm\":-20},\"nullCount\":{\"reading_id\":0,\"sensor_id\":0,\"timestamp_ms\":0,\"location\":{\"latitude\":0,\"longitude\":0,\"altitude_meters\":358,\"place_name\":0},\"precipitation_mm\":3883,\"rain_intensity\":0,\"is_raining\":3883,\"temperature_celsius\":4,\"humidity_percent\":0,\"pressure_hpa\":0,\"wind_speed_kmh\":0,\"wind_direction_degrees\":1,\"battery_level_percent\":0,\"signal_strength_dbm\":0}}"}}
{"add":{"path":"part-00010-60733327-ca92-439f-86ca-43e48cb769ea-c000.snappy.parquet","partitionValues":{},"size":361449,"modificationTime":1776448146663,"dataChange":true,"stats":"{\"numRecords\":7168,\"minValues\":{\"reading_id\":\"0006de5d-0efd-b673-2aed-13991136\",\"sensor_id\":\"2c386245-7993-6340-58de-21d43312\",\"timestamp_ms\":1758983040000,\"location\":{\"latitude\":-45.4148,\"longitude\":-159.3711,\"altitude_meters\":-86.0,\"place_name\":\"Bergen, Vestland, Norway\"},\"precipitation_mm\":0.01,\"rain_intensity\":\"RAIN_INTENSITY_HEAVY\",\"temperature_celsius\":-14.8,\"humidity_percent\":3.0,\"pressure_hpa\":758.1,\"wind_speed_kmh\":1.0,\"wind_direction_degrees\":0.1,\"battery_level_percent\":5,\"signal_strength_dbm\":-95},\"maxValues\":{\"reading_id\":\"fffd37da-1617-3b33-662a-c08a454c\",\"sensor_id\":\"ffb43aae-7b42-f1f1-03b6-3d56a2a7\",\"timestamp_ms\":1759434120000,\"location\":{\"latitude\":64.1466,\"longitude\":167.7181,\"altitude_meters\":2400.0,\"place_name\":\"Tokyo, Kantō, Japan\"},\"precipitation_mm\":13.77,\"rain_intensity\":\"RAIN_INTENSITY_NONE\",\"temperature_celsius\":51.9,\"humidity_percent\":100.0,\"pressure_hpa\":1027.0,\"wind_speed_kmh\":72.6,\"wind_direction_degrees\":359.8,\"battery_level_percent\":5,\"signal_strength_dbm\":-20},\"nullCount\":{\"reading_id\":0,\"sensor_id\":0,\"timestamp_ms\":0,\"location\":{\"latitude\":0,\"longitude\":0,\"altitude_meters\":358,\"place_name\":0},\"precipitation_mm\":3808,\"rain_intensity\":0,\"is_raining\":3808,\"temperature_celsius\":5,\"humidity_percent\":0,\"pressure_hpa\":0,\"wind_speed_kmh\":0,\"wind_direction_degrees\":1,\"battery_level_percent\":0,\"signal_strength_dbm\":0}}"}}
{"add":{"path":"part-00011-93ce548b-8588-4b98-b36d-eba6488e8c48-c000.snappy.parquet","partitionValues":{},"size":360921,"modificationTime":1776448146670,"dataChange":true,"stats":"{\"numRecords\":7168,\"minValues\":{\"reading_id\":\"000b009e-6300-ee3e-3f4c-9c794136\",\"sensor_id\":\"2c386245-7993-6340-58de-21d43312\",\"timestamp_ms\":1759434120000,\"location\":{\"latitude\":-45.4148,\"longitude\":-159.3711,\"altitude_meters\":-86.0,\"place_name\":\"Bergen, Vestland, Norway\"},\"precipitation_mm\":0.01,\"rain_intensity\":\"RAIN_INTENSITY_HEAVY\",\"temperature_celsius\":-15.0,\"humidity_percent\":3.0,\"pressure_hpa\":756.8,\"wind_speed_kmh\":1.1,\"wind_direction_degrees\":0.1,\"battery_level_percent\":5,\"signal_strength_dbm\":-95},\"maxValues\":{\"reading_id\":\"fffe6aac-73ec-c5e4-8159-82c7d1b4\",\"sensor_id\":\"ffb43aae-7b42-f1f1-03b6-3d56a2a7\",\"timestamp_ms\":1759885200000,\"location\":{\"latitude\":64.1466,\"longitude\":167.7181,\"altitude_meters\":2400.0,\"place_name\":\"Tokyo, Kantō, Japan\"},\"precipitation_mm\":13.67,\"rain_intensity\":\"RAIN_INTENSITY_NONE\",\"temperature_celsius\":52.0,\"humidity_percent\":100.0,\"pressure_hpa\":1027.0,\"wind_speed_kmh\":75.2,\"wind_direction_degrees\":359.9,\"battery_level_percent\":5,\"signal_strength_dbm\":-20},\"nullCount\":{\"reading_id\":0,\"sensor_id\":0,\"timestamp_ms\":0,\"location\":{\"latitude\":0,\"longitude\":0,\"altitude_meters\":359,\"place_name\":0},\"precipitation_mm\":3883,\"rain_intensity\":0,\"is_raining\":3883,\"temperature_celsius\":3,\"humidity_percent\":0,\"pressure_hpa\":0,\"wind_speed_kmh\":0,\"wind_direction_degrees\":1,\"battery_level_percent\":0,\"signal_strength_dbm\":0}}"}}
{"add":{"path":"part-00012-d8c8a678-c084-4606-86ae-d002dc0f34d9-c000.snappy.parquet","partitionValues":{},"size":361307,"modificationTime":1776448146664,"dataChange":true,"stats":"{\"numRecords\":7168,\"minValues\":{\"reading_id\":\"00105a9b-c560-0915-a908-4edff2de\",\"sensor_id\":\"2c386245-7993-6340-58de-21d43312\",\"timestamp_ms\":1759885200000,\"location\":{\"latitude\":-45.4148,\"longitude\":-159.3711,\"altitude_meters\":-86.0,\"place_name\":\"Bergen, Vestland, Norway\"},\"precipitation_mm\":0.01,\"rain_intensity\":\"RAIN_INTENSITY_HEAVY\",\"temperature_celsius\":-14.9,\"humidity_percent\":3.0,\"pressure_hpa\":756.1,\"wind_speed_kmh\":1.0,\"wind_direction_degrees\":0.1,\"battery_level_percent\":5,\"signal_strength_dbm\":-95},\"maxValues\":{\"reading_id\":\"ffff1cc4-562f-0e7e-2922-2057898f\",\"sensor_id\":\"ffb43aae-7b42-f1f1-03b6-3d56a2a7\",\"timestamp_ms\":1760337540000,\"location\":{\"latitude\":64.1466,\"longitude\":167.7181,\"altitude_meters\":2400.0,\"place_name\":\"Tokyo, Kantō, Japan\"},\"precipitation_mm\":12.93,\"rain_intensity\":\"RAIN_INTENSITY_NONE\",\"temperature_celsius\":51.4,\"humidity_percent\":100.0,\"pressure_hpa\":1027.0,\"wind_speed_kmh\":66.1,\"wind_direction_degrees\":359.8,\"battery_level_percent\":5,\"signal_strength_dbm\":-20},\"nullCount\":{\"reading_id\":0,\"sensor_id\":0,\"timestamp_ms\":0,\"location\":{\"latitude\":0,\"longitude\":0,\"altitude_meters\":358,\"place_name\":0},\"precipitation_mm\":3836,\"rain_intensity\":0,\"is_raining\":3836,\"temperature_celsius\":5,\"humidity_percent\":0,\"pressure_hpa\":0,\"wind_speed_kmh\":0,\"wind_direction_degrees\":0,\"battery_level_percent\":0,\"signal_strength_dbm\":0}}"}}
{"add":{"path":"part-00013-de102b5b-0336-4ad8-b7c2-c811c0b34a82-c000.snappy.parquet","partitionValues":{},"size":344624,"modificationTime":1776448146681,"dataChange":true,"stats":"{\"numRecords\":6816,\"minValues\":{\"reading_id\":\"0004a60b-bc0d-d9f1-3866-27588d2e\",\"sensor_id\":\"2c386245-7993-6340-58de-21d43312\",\"timestamp_ms\":1760337540000,\"location\":{\"latitude\":-45.4148,\"longitude\":-159.3711,\"altitude_meters\":-86.0,\"place_name\":\"Bergen, Vestland, Norway\"},\"precipitation_mm\":0.03,\"rain_intensity\":\"RAIN_INTENSITY_HEAVY\",\"temperature_celsius\":-14.8,\"humidity_percent\":3.1,\"pressure_hpa\":756.2,\"wind_speed_kmh\":1.0,\"wind_direction_degrees\":0.1,\"battery_level_percent\":5,\"signal_strength_dbm\":-95},\"maxValues\":{\"reading_id\":\"ffff7281-b0d4-6071-b8c3-de9a642b\",\"sensor_id\":\"ffb43aae-7b42-f1f1-03b6-3d56a2a7\",\"timestamp_ms\":1760765940000,\"location\":{\"latitude\":64.1466,\"longitude\":167.7181,\"altitude_meters\":2400.0,\"place_name\":\"Tokyo, Kantō, Japan\"},\"precipitation_mm\":13.51,\"rain_intensity\":\"RAIN_INTENSITY_NONE\",\"temperature_celsius\":52.0,\"humidity_percent\":100.0,\"pressure_hpa\":1027.0,\"wind_speed_kmh\":65.0,\"wind_direction_degrees\":359.8,\"battery_level_percent\":5,\"signal_strength_dbm\":-20},\"nullCount\":{\"reading_id\":0,\"sensor_id\":0,\"timestamp_ms\":0,\"location\":{\"latitude\":0,\"longitude\":0,\"altitude_meters\":341,\"place_name\":0},\"precipitation_mm\":3602,\"rain_intensity\":0,\"is_raining\":3602,\"temperature_celsius\":2,\"humidity_percent\":0,\"pressure_hpa\":0,\"wind_speed_kmh\":0,\"wind_direction_degrees\":1,\"battery_level_percent\":0,\"signal_strength_dbm\":0}}"}}
